MANIFEST.in
README.rst
setup.py
.tx/config
collective/__init__.py
collective.navigationtoggle.egg-info/PKG-INFO
collective.navigationtoggle.egg-info/SOURCES.txt
collective.navigationtoggle.egg-info/dependency_links.txt
collective.navigationtoggle.egg-info/entry_points.txt
collective.navigationtoggle.egg-info/namespace_packages.txt
collective.navigationtoggle.egg-info/not-zip-safe
collective.navigationtoggle.egg-info/requires.txt
collective.navigationtoggle.egg-info/top_level.txt
collective/navigationtoggle/__init__.py
collective/navigationtoggle/configure.zcml
collective/navigationtoggle/interfaces.py
collective/navigationtoggle/setuphandlers.py
collective/navigationtoggle/testing.py
collective/navigationtoggle/upgrades.zcml
collective/navigationtoggle/Extensions/install.py
collective/navigationtoggle/browser/__init__.py
collective/navigationtoggle/browser/collective.navigationtoggle.js
collective/navigationtoggle/browser/configure.zcml
collective/navigationtoggle/browser/controlpanel.py
collective/navigationtoggle/browser/query_subelements.py
collective/navigationtoggle/browser/registered_filters.py
collective/navigationtoggle/browser/images/toggle.png
collective/navigationtoggle/locales/collective.navigationtoggle-manual.pot
collective/navigationtoggle/locales/collective.navigationtoggle.pot
collective/navigationtoggle/locales/rebuildPo.sh
collective/navigationtoggle/locales/es/LC_MESSAGES/collective.navigationtoggle.po
collective/navigationtoggle/locales/it/LC_MESSAGES/collective.navigationtoggle.po
collective/navigationtoggle/profiles/default/browserlayer.xml
collective/navigationtoggle/profiles/default/collective.navigationtoggle.txt
collective/navigationtoggle/profiles/default/controlpanel.xml
collective/navigationtoggle/profiles/default/import_steps.xml
collective/navigationtoggle/profiles/default/jsregistry.xml
collective/navigationtoggle/profiles/default/metadata.xml
collective/navigationtoggle/profiles/default/registry.xml
collective/navigationtoggle/profiles/default/rolemap.xml
collective/navigationtoggle/profiles/uninstall/browserlayer.xml
collective/navigationtoggle/profiles/uninstall/controlpanel.xml
collective/navigationtoggle/profiles/uninstall/jsregistry.xml
collective/navigationtoggle/profiles/uninstall/registry.xml
collective/navigationtoggle/tests/__init__.py
collective/navigationtoggle/tests/test_configuration_js_view.py
