Metadata-Version: 2.1
Name: collective.navigationtoggle
Version: 1.0.3
Summary: Expand/collapse feature for specific Plone navigation entries, in an unobtrusive way
Home-page: http://plone.org/products/collective.navigationtoggle
Author: RedTurtle Technology
Author-email: sviluppoplone@redturtle.it
License: GPL
Keywords: plone plonegov jquery navigation javascript
Platform: UNKNOWN
Classifier: Framework :: Plone
Classifier: Framework :: Plone :: 3.3
Classifier: Framework :: Plone :: 4.0
Classifier: Framework :: Plone :: 4.1
Classifier: Framework :: Plone :: 4.2
Classifier: Framework :: Plone :: 4.3
Classifier: Programming Language :: Python
Classifier: Programming Language :: JavaScript
Classifier: Development Status :: 5 - Production/Stable
Provides-Extra: test
